budosystems/xtra/mypy_plugin/__init__.py
budosystems/xtra/mypy_plugin/_plugin.py
budosystems/xtra/mypy_plugin/_version.py
budosystems/xtra/mypy_plugin/py.typed
budosystems/xtra/mypy_plugin/sample.py
mypy_budosystems-0.6.3.dist-info/LICENCE.txt
mypy_budosystems-0.6.3.dist-info/METADATA
mypy_budosystems-0.6.3.dist-info/WHEEL
mypy_budosystems-0.6.3.dist-info/top_level.txt
mypy_budosystems-0.6.3.dist-info/RECORD
